pyOfficeSheet/__init__.py
pyOfficeSheet/__main__.py
pyOfficeSheet/config.json
pyOfficeSheet/entry.py
pyOfficeSheet/py-office-sheet.AppImage
pyOfficeSheet/py-office-sheet.exe
pyOfficeSheet/spreadsheet_command.py
pyOfficeSheet/pic/icon/240px-Refresh_icon.png
pyOfficeSheet/pic/icon/Refresh_icon.png
pyOfficeSheet/pic/icon/cellResize.png
pyOfficeSheet/pic/icon/cut_icon.png
pyOfficeSheet/pic/icon/execute.png
pyOfficeSheet/pic/icon/exportCSV.png
pyOfficeSheet/pic/icon/exportPDF.png
pyOfficeSheet/pic/icon/file.jpeg
pyOfficeSheet/pic/icon/file.png
pyOfficeSheet/pic/icon/link_sync.png
pyOfficeSheet/pic/icon/main.png
pyOfficeSheet/pic/icon/newFile.png
pyOfficeSheet/pic/icon/printer.png
pyOfficeSheet/pic/icon/py-office-icon_small.png
pyOfficeSheet/pic/icon/pyoffice.png
pyOfficeSheet/pic/icon/save.png
pyOfficeSheet/pic/icon/user.png
pyOfficeSheet/pic/icon/warning.png
py_office_sheet-0.1.195.dist-info/LICENSE
py_office_sheet-0.1.195.dist-info/METADATA
py_office_sheet-0.1.195.dist-info/WHEEL
py_office_sheet-0.1.195.dist-info/entry_points.txt
py_office_sheet-0.1.195.dist-info/top_level.txt
py_office_sheet-0.1.195.dist-info/RECORD
