Metadata-Version: 2.1
Name: py-office-sheet
Version: 0.1.195
Summary: py-office-sheet is a gui based on pandas and numpy to process data efficienly
Home-page: https://github.com/YC-Lammy/py-office-sheet
Author: YC
Author-email: yclam508@protonmail.com
License: GPL
Platform: Linux
Platform: Mac OS X
Platform: Windows
Classifier: License :: OSI Approved :: GNU General Public License v3 (GPLv3)
Classifier: Programming Language :: Python :: 3
Classifier: Programming Language :: Python :: 3.7
Classifier: Programming Language :: Python :: 3.8
Classifier: Programming Language :: Python :: 3.9
Classifier: Programming Language :: Python :: 3 :: Only
Requires-Dist: PySide2
Requires-Dist: joblib
Requires-Dist: matplotlib
Requires-Dist: numpy
Requires-Dist: pandas
Requires-Dist: pyshortcuts
